Single_Cycle/Module1_1b_RegFile/regfile.sv
module regfile (
    input logic clk,
    input logic rst_n,

    //Reading to regfile
    input logic [4:0] rs1, //Address of source register 1
    input logic [4:0] rs2, //Address of source register 2
    output logic [31:0] read_data1, //Data read from source register 1
    output logic [31:0] read_data2, //Data read from source register

    //Writing to regfile
    input logic write_enable, //Enable signal for writing to the register file
    input logic [31:0] write_data,
    input logic [4:0] rs3

);

//32 bit registers, 32 registers in total, each address being 5-bits wide
reg [31:0] registers [0:31]; 

//Write regfile logic
always @(posedge clk) begin
    //Reset or else init to 0
    if (!rst_n) begin
        for (int i =0; i < 32; i++) begin
            registers[i] <= 32'b0; //Initializes all registers to 0 on reset
        end
    end

    //Write except on 0, its reserved for the 0 constant based on the RISC-V spec
    else if (write_enable && rs3 != 0) begin
        registers[rs3] <= write_data; //Writes the data to the register at the specific address
    end

end

//Read logic, asynchronous of clock
always_comb begin: readLogic
    read_data1 = registers[rs1]; //Reads the data from the register at the specific address for source register 1
    read_data2 = registers[rs2]; //Reads the data from the register at the specific address for source register 2
end

endmodule

Single_Cycle/Module1_1b_RegFile/dump.vcd
$version Generated by VerilatedVcd $end
$timescale 1ps $end
 $scope module $rootio $end
  $var wire 1 " clk $end
  $var wire 1 # rst_n $end
  $var wire 5 $ rs1 [4:0] $end
  $var wire 5 % rs2 [4:0] $end
  $var wire 32 & read_data1 [31:0] $end
  $var wire 32 ' read_data2 [31:0] $end
  $var wire 1 ( write_enable $end
  $var wire 32 ) write_data [31:0] $end
  $var wire 5 * rs3 [4:0] $end
 $upscope $end
 $scope module regfile $end
  $var wire 1 + clk $end
  $var wire 1 , rst_n $end
  $var wire 5 - rs1 [4:0] $end
  $var wire 5 . rs2 [4:0] $end
  $var wire 32 / read_data1 [31:0] $end
  $var wire 32 0 read_data2 [31:0] $end
  $var wire 1 1 write_enable $end
  $var wire 32 2 write_data [31:0] $end
  $var wire 5 3 rs3 [4:0] $end
  $var wire 32 4 registers[0] [31:0] $end
  $var wire 32 5 registers[1] [31:0] $end
  $var wire 32 6 registers[2] [31:0] $end
  $var wire 32 7 registers[3] [31:0] $end
  $var wire 32 8 registers[4] [31:0] $end
  $var wire 32 9 registers[5] [31:0] $end
  $var wire 32 : registers[6] [31:0] $end
  $var wire 32 ; registers[7] [31:0] $end
  $var wire 32 < registers[8] [31:0] $end
  $var wire 32 = registers[9] [31:0] $end
  $var wire 32 > registers[10] [31:0] $end
  $var wire 32 ? registers[11] [31:0] $end
  $var wire 32 @ registers[12] [31:0] $end
  $var wire 32 A registers[13] [31:0] $end
  $var wire 32 B registers[14] [31:0] $end
  $var wire 32 C registers[15] [31:0] $end
  $var wire 32 D registers[16] [31:0] $end
  $var wire 32 E registers[17] [31:0] $end
  $var wire 32 F registers[18] [31:0] $end
  $var wire 32 G registers[19] [31:0] $end
  $var wire 32 H registers[20] [31:0] $end
  $var wire 32 I registers[21] [31:0] $end
  $var wire 32 J registers[22] [31:0] $end
  $var wire 32 K registers[23] [31:0] $end
  $var wire 32 L registers[24] [31:0] $end
  $var wire 32 M registers[25] [31:0] $end
  $var wire 32 N registers[26] [31:0] $end
  $var wire 32 O registers[27] [31:0] $end
  $var wire 32 P registers[28] [31:0] $end
  $var wire 32 Q registers[29] [31:0] $end
  $var wire 32 R registers[30] [31:0] $end
  $var wire 32 S registers[31] [31:0] $end
 $upscope $end
$enddefinitions $end


#0
1"
0#
b00000 $
b00000 %
b00000000000000000000000000000000 &
b00000000000000000000000000000000 '
0(
b00000000000000000000000000000000 )
b00000 *
1+
0,
b00000 -
b00000 .
b00000000000000000000000000000000 /
b00000000000000000000000000000000 0
01
b00000000000000000000000000000000 2
b00000 3
b00000000000000000000000000000000 4
b00000000000000000000000000000000 5
b00000000000000000000000000000000 6
b00000000000000000000000000000000 7
b00000000000000000000000000000000 8
b00000000000000000000000000000000 9
b00000000000000000000000000000000 :
b00000000000000000000000000000000 ;
b00000000000000000000000000000000 <
b00000000000000000000000000000000 =
b00000000000000000000000000000000 >
b00000000000000000000000000000000 ?
b00000000000000000000000000000000 @
b00000000000000000000000000000000 A
b00000000000000000000000000000000 B
b00000000000000000000000000000000 C
b00000000000000000000000000000000 D
b00000000000000000000000000000000 E
b00000000000000000000000000000000 F
b00000000000000000000000000000000 G
b00000000000000000000000000000000 H
b00000000000000000000000000000000 I
b00000000000000000000000000000000 J
b00000000000000000000000000000000 K
b00000000000000000000000000000000 L
b00000000000000000000000000000000 M
b00000000000000000000000000000000 N
b00000000000000000000000000000000 O
b00000000000000000000000000000000 P
b00000000000000000000000000000000 Q
b00000000000000000000000000000000 R
b00000000000000000000000000000000 S
#5000
0"
0+
#10000
1"
1#
1+
1,
#15000
0"
0+
#20000
1"
1+
#21000
b00100 $
b11010 %
b00100 -
b11010 .
#22000
1(
b11000000101111000101011001000000 )
b01100 *
11
b11000000101111000101011001000000 2
b01100 3
#25000
0"
0+
#30000
1"
0(
1+
01
b11000000101111000101011001000000 @
#32000
b01010 $
b00010 %
b01010 -
b00010 .
#33000
1(
b00100110000101011110011101100001 )
b00010 *
11
b00100110000101011110011101100001 2
b00010 3
#35000
0"
0+
#40000
1"
b00100110000101011110011101100001 '
0(
1+
b00100110000101011110011101100001 0
01
b00100110000101011110011101100001 6
#42000
b11000 $
b11000 %
b00000000000000000000000000000000 '
b11000 -
b11000 .
b00000000000000000000000000000000 0
#43000
1(
b10010001110010110110100011011101 )
b01110 *
11
b10010001110010110110100011011101 2
b01110 3
#45000
0"
0+
#50000
1"
0(
1+
01
b10010001110010110110100011011101 B
#52000
b10010 $
b00010 %
b00100110000101011110011101100001 '
b10010 -
b00010 .
b00100110000101011110011101100001 0
#53000
1(
b01100010010010011010010010100001 )
b11001 *
11
b01100010010010011010010010100001 2
b11001 3
#55000
0"
0+
#60000
1"
0(
1+
01
b01100010010010011010010010100001 M
#62000
b10001 $
b00011 %
b00000000000000000000000000000000 '
b10001 -
b00011 .
b00000000000000000000000000000000 0
#63000
1(
b00010110110110100101010011110000 )
b01000 *
11
b00010110110110100101010011110000 2
b01000 3
#65000
0"
0+
#70000
1"
0(
1+
01
b00010110110110100101010011110000 <
#72000
b11100 $
b01000 %
b00010110110110100101010011110000 '
b11100 -
b01000 .
b00010110110110100101010011110000 0
#73000
1(
b10001100000110110000000000010000 )
11
b10001100000110110000000000010000 2
#75000
0"
0+
#80000
1"
b10001100000110110000000000010000 '
0(
1+
b10001100000110110000000000010000 0
01
b10001100000110110000000000010000 <
#82000
b01011 $
b10001 %
b00000000000000000000000000000000 '
b01011 -
b10001 .
b00000000000000000000000000000000 0
#83000
1(
b10100110001011111101101001000010 )
b11001 *
11
b10100110001011111101101001000010 2
b11001 3
#85000
0"
0+
#90000
1"
0(
1+
01
b10100110001011111101101001000010 M
#92000
b10011 $
b00001 %
b10011 -
b00001 .
#93000
1(
b01100001100000011101100111010101 )
b10101 *
11
b01100001100000011101100111010101 2
b10101 3
#95000
0"
0+
#100000
1"
0(
1+
01
b01100001100000011101100111010101 I
#102000
b10101 $
b10000 %
b01100001100000011101100111010101 &
b10101 -
b10000 .
b01100001100000011101100111010101 /
#103000
1(
b01100010010111110101000100000110 )
b01001 *
11
b01100010010111110101000100000110 2
b01001 3
#105000
0"
0+
#110000
1"
0(
1+
01
b01100010010111110101000100000110 =
#112000
b10010 $
b00101 %
b00000000000000000000000000000000 &
b10010 -
b00101 .
b00000000000000000000000000000000 /
#113000
1(
b11110111010010111000001101011010 )
b01000 *
11
b11110111010010111000001101011010 2
b01000 3
#115000
0"
0+
#120000
1"
0(
1+
01
b11110111010010111000001101011010 <
#122000
b10001 $
b01010 %
b10001 -
b01010 .
#123000
1(
b01110101000010001010001000001101 )
b01111 *
11
b01110101000010001010001000001101 2
b01111 3
#125000
0"
0+
#130000
1"
0(
1+
01
b01110101000010001010001000001101 C
#132000
b11100 $
b11110 %
b11100 -
b11110 .
#133000
1(
b11111110111100010110001101000100 )
b11001 *
11
b11111110111100010110001101000100 2
b11001 3
#135000
0"
0+
#140000
1"
0(
1+
01
b11111110111100010110001101000100 M
#142000
b00111 %
b00111 .
#143000
1(
b10001100001111101001100100000010 )
b10101 *
11
b10001100001111101001100100000010 2
b10101 3
#145000
0"
0+
#150000
1"
0(
1+
01
b10001100001111101001100100000010 I
#152000
b00001 $
b11111 %
b00001 -
b11111 .
#153000
1(
b10000111110110001101001001000101 )
b11110 *
11
b10000111110110001101001001000101 2
b11110 3
#155000
0"
0+
#160000
1"
0(
1+
01
b10000111110110001101001001000101 R
#162000
b00010 $
b10000 %
b00100110000101011110011101100001 &
b00010 -
b10000 .
b00100110000101011110011101100001 /
#163000
1(
b10101000101010101000101110001010 )
b10101 *
11
b10101000101010101000101110001010 2
b10101 3
#165000
0"
0+
#170000
1"
0(
1+
01
b10101000101010101000101110001010 I
#172000
b00111 $
b00010 %
b00000000000000000000000000000000 &
b00100110000101011110011101100001 '
b00111 -
b00010 .
b00000000000000000000000000000000 /
b00100110000101011110011101100001 0
#173000
1(
b10101101011011111111111011100110 )
b11110 *
11
b10101101011011111111111011100110 2
b11110 3
#175000
0"
0+
#180000
1"
0(
1+
01
b10101101011011111111111011100110 R
#182000
b11000 $
b00111 %
b00000000000000000000000000000000 '
b11000 -
b00111 .
b00000000000000000000000000000000 0
#183000
1(
b10111100101110000011100001001010 )
b01100 *
11
b10111100101110000011100001001010 2
b01100 3
#185000
0"
0+
#190000
1"
0(
1+
01
b10111100101110000011100001001010 @
#192000
b00111 $
b00111 -
#193000
1(
b11110100100110110101111010111101 )
b11010 *
11
b11110100100110110101111010111101 2
b11010 3
#195000
0"
0+
#200000
1"
0(
1+
01
b11110100100110110101111010111101 N
#202000
b10001 $
b00101 %
b10001 -
b00101 .
#203000
1(
b00001110010100011010001101111000 )
b00100 *
11
b00001110010100011010001101111000 2
b00100 3
#205000
0"
0+
#210000
1"
0(
1+
01
b00001110010100011010001101111000 8
#212000
b11001 $
b10110 %
b11111110111100010110001101000100 &
b11001 -
b10110 .
b11111110111100010110001101000100 /
#213000
1(
b01001011000101101110001001010001 )
b01100 *
11
b01001011000101101110001001010001 2
b01100 3
#215000
0"
0+
#220000
1"
0(
1+
01
b01001011000101101110001001010001 @
#222000
b00110 $
b10011 %
b00000000000000000000000000000000 &
b00110 -
b10011 .
b00000000000000000000000000000000 /
#223000
1(
b01111111111011111110000001001000 )
b11111 *
11
b01111111111011111110000001001000 2
b11111 3
#225000
0"
0+
#230000
1"
0(
1+
01
b01111111111011111110000001001000 S
#232000
b00111 $
b00110 %
b00111 -
b00110 .
#233000
1(
b10101111101010011110001010010001 )
b00101 *
11
b10101111101010011110001010010001 2
b00101 3
#235000
0"
0+
#240000
1"
0(
1+
01
b10101111101010011110001010010001 9
#242000
b11110 $
b01110 %
b10101101011011111111111011100110 &
b10010001110010110110100011011101 '
b11110 -
b01110 .
b10101101011011111111111011100110 /
b10010001110010110110100011011101 0
#243000
1(
b11010010101101110111101111000101 )
b01001 *
11
b11010010101101110111101111000101 2
b01001 3
#245000
0"
0+
#250000
1"
0(
1+
01
b11010010101101110111101111000101 =
#252000
b11010 $
b00011 %
b11110100100110110101111010111101 &
b00000000000000000000000000000000 '
b11010 -
b00011 .
b11110100100110110101111010111101 /
b00000000000000000000000000000000 0
#253000
1(
b11111000110100011111110111011110 )
b10011 *
11
b11111000110100011111110111011110 2
b10011 3
#255000
0"
0+
#260000
1"
0(
1+
01
b11111000110100011111110111011110 G
#262000
b10000 $
b10001 %
b00000000000000000000000000000000 &
b10000 -
b10001 .
b00000000000000000000000000000000 /
#263000
1(
b01000010110100010001101110000001 )
b11001 *
11
b01000010110100010001101110000001 2
b11001 3
#265000
0"
0+
#270000
1"
0(
1+
01
b01000010110100010001101110000001 M
#272000
b10010 $
b10010 %
b10010 -
b10010 .
#273000
1(
b10111011010111011011011000111011 )
11
b10111011010111011011011000111011 2
#275000
0"
0+
#280000
1"
0(
1+
01
b10111011010111011011011000111011 M
#282000
b01011 $
b00001 %
b01011 -
b00001 .
#283000
1(
b00101001001010110011001001111100 )
b11010 *
11
b00101001001010110011001001111100 2
b11010 3
#285000
0"
0+
#290000
1"
0(
1+
01
b00101001001010110011001001111100 N
#292000
b11010 $
b11001 %
b00101001001010110011001001111100 &
b10111011010111011011011000111011 '
b11010 -
b11001 .
b00101001001010110011001001111100 /
b10111011010111011011011000111011 0
#293000
1(
b01110010010011110111010010110101 )
b10010 *
11
b01110010010011110111010010110101 2
b10010 3
#295000
0"
0+
#300000
1"
0(
1+
01
b01110010010011110111010010110101 F
#302000
b11100 $
b00010 %
b00000000000000000000000000000000 &
b00100110000101011110011101100001 '
b11100 -
b00010 .
b00000000000000000000000000000000 /
b00100110000101011110011101100001 0
#303000
1(
b11110010011111101110101011110001 )
b00110 *
11
b11110010011111101110101011110001 2
b00110 3
#305000
0"
0+
#310000
1"
0(
1+
01
b11110010011111101110101011110001 :
#312000
b11010 $
b01010 %
b00101001001010110011001001111100 &
b00000000000000000000000000000000 '
b11010 -
b01010 .
b00101001001010110011001001111100 /
b00000000000000000000000000000000 0
#313000
1(
b11111001011011110111110011101101 )
b00011 *
11
b11111001011011110111110011101101 2
b00011 3
#315000
0"
0+
#320000
1"
0(
1+
01
b11111001011011110111110011101101 7
#322000
b11011 $
b01000 %
b00000000000000000000000000000000 &
b11110111010010111000001101011010 '
b11011 -
b01000 .
b00000000000000000000000000000000 /
b11110111010010111000001101011010 0
#323000
1(
b11111110001000011011101010111011 )
b10100 *
11
b11111110001000011011101010111011 2
b10100 3
#325000
0"
0+
#330000
1"
0(
1+
01
b11111110001000011011101010111011 H
#332000
b11110 $
b11010 %
b10101101011011111111111011100110 &
b00101001001010110011001001111100 '
b11110 -
b11010 .
b10101101011011111111111011100110 /
b00101001001010110011001001111100 0
#333000
1(
b01001110000010001000001001111101 )
b01101 *
11
b01001110000010001000001001111101 2
b01101 3
#335000
0"
0+
#340000
1"
0(
1+
01
b01001110000010001000001001111101 A
#342000
b01101 $
b01000 %
b01001110000010001000001001111101 &
b11110111010010111000001101011010 '
b01101 -
b01000 .
b01001110000010001000001001111101 /
b11110111010010111000001101011010 0
#343000
1(
b10010000001111000111010111110101 )
b10100 *
11
b10010000001111000111010111110101 2
b10100 3
#345000
0"
0+
#350000
1"
0(
1+
01
b10010000001111000111010111110101 H
#352000
b00111 $
b01101 %
b00000000000000000000000000000000 &
b01001110000010001000001001111101 '
b00111 -
b01101 .
b00000000000000000000000000000000 /
b01001110000010001000001001111101 0
#353000
1(
b10100100111001100111100001001111 )
b11001 *
11
b10100100111001100111100001001111 2
b11001 3
#355000
0"
0+
#360000
1"
0(
1+
01
b10100100111001100111100001001111 M
#362000
b11010 $
b10100 %
b00101001001010110011001001111100 &
b10010000001111000111010111110101 '
b11010 -
b10100 .
b00101001001010110011001001111100 /
b10010000001111000111010111110101 0
#363000
1(
b00000100000000111000100110111000 )
b00111 *
11
b00000100000000111000100110111000 2
b00111 3
#365000
0"
0+
#370000
1"
0(
1+
01
b00000100000000111000100110111000 ;
#372000
b00100 $
b01101 %
b00001110010100011010001101111000 &
b01001110000010001000001001111101 '
b00100 -
b01101 .
b00001110010100011010001101111000 /
b01001110000010001000001001111101 0
#373000
1(
b01111010000011111000111110011000 )
b01111 *
11
b01111010000011111000111110011000 2
b01111 3
#375000
0"
0+
#380000
1"
0(
1+
01
b01111010000011111000111110011000 C
#382000
b10000 $
b10001 %
b00000000000000000000000000000000 &
b00000000000000000000000000000000 '
b10000 -
b10001 .
b00000000000000000000000000000000 /
b00000000000000000000000000000000 0
#383000
1(
b01101001100110110111111111000111 )
b01110 *
11
b01101001100110110111111111000111 2
b01110 3
#385000
0"
0+
#390000
1"
0(
1+
01
b01101001100110110111111111000111 B
#392000
b01111 $
b10000 %
b01111010000011111000111110011000 &
b01111 -
b10000 .
b01111010000011111000111110011000 /
#393000
1(
b01011010011011100101100111100101 )
b01010 *
11
b01011010011011100101100111100101 2
b01010 3
#395000
0"
0+
#400000
1"
0(
1+
01
b01011010011011100101100111100101 >
#402000
b01000 $
b10001 %
b11110111010010111000001101011010 &
b01000 -
b10001 .
b11110111010010111000001101011010 /
#403000
1(
b11000001000001101000010110100111 )
b11110 *
11
b11000001000001101000010110100111 2
b11110 3
#405000
0"
0+
#410000
1"
0(
1+
01
b11000001000001101000010110100111 R
#412000
b00111 $
b00001 %
b00000100000000111000100110111000 &
b00111 -
b00001 .
b00000100000000111000100110111000 /
#413000
1(
b10100001101110100101000001111010 )
b11111 *
11
b10100001101110100101000001111010 2
b11111 3
#415000
0"
0+
#420000
1"
0(
1+
01
b10100001101110100101000001111010 S
#422000
b10011 $
b11010 %
b11111000110100011111110111011110 &
b00101001001010110011001001111100 '
b10011 -
b11010 .
b11111000110100011111110111011110 /
b00101001001010110011001001111100 0
#423000
1(
b00110111111100111000101111111010 )
b10010 *
11
b00110111111100111000101111111010 2
b10010 3
#425000
0"
0+
#430000
1"
0(
1+
01
b00110111111100111000101111111010 F
#432000
b10110 $
b10111 %
b00000000000000000000000000000000 &
b00000000000000000000000000000000 '
b10110 -
b10111 .
b00000000000000000000000000000000 /
b00000000000000000000000000000000 0
#433000
1(
b00100011100001111011000100010011 )
b00010 *
11
b00100011100001111011000100010011 2
b00010 3
#435000
0"
0+
#440000
1"
0(
1+
01
b00100011100001111011000100010011 6
#442000
b10011 $
b00111 %
b11111000110100011111110111011110 &
b00000100000000111000100110111000 '
b10011 -
b00111 .
b11111000110100011111110111011110 /
b00000100000000111000100110111000 0
#443000
1(
b00000000111100110011001010000111 )
b10001 *
11
b00000000111100110011001010000111 2
b10001 3
#445000
0"
0+
#450000
1"
0(
1+
01
b00000000111100110011001010000111 E
#452000
b11010 $
b11010 %
b00101001001010110011001001111100 &
b00101001001010110011001001111100 '
b11010 -
b11010 .
b00101001001010110011001001111100 /
b00101001001010110011001001111100 0
#453000
1(
b11011001011011010111010001111010 )
b00010 *
11
b11011001011011010111010001111010 2
b00010 3
#455000
0"
0+
#460000
1"
0(
1+
01
b11011001011011010111010001111010 6
#462000
b11101 $
b00000000000000000000000000000000 &
b11101 -
b00000000000000000000000000000000 /
#463000
1(
b11100010001101101011111011001001 )
b01101 *
11
b11100010001101101011111011001001 2
b01101 3
#465000
0"
0+
#470000
1"
0(
1+
01
b11100010001101101011111011001001 A
#472000
b00101 $
b01111 %
b10101111101010011110001010010001 &
b01111010000011111000111110011000 '
b00101 -
b01111 .
b10101111101010011110001010010001 /
b01111010000011111000111110011000 0
#473000
1(
b01111011111001011101010011101010 )
b10101 *
11
b01111011111001011101010011101010 2
b10101 3
#475000
0"
0+
#480000
1"
0(
1+
01
b01111011111001011101010011101010 I
#482000
b11110 $
b00010 %
b11000001000001101000010110100111 &
b11011001011011010111010001111010 '
b11110 -
b00010 .
b11000001000001101000010110100111 /
b11011001011011010111010001111010 0
#483000
1(
b11001011000110110000101010000110 )
b01110 *
11
b11001011000110110000101010000110 2
b01110 3
#485000
0"
0+
#490000
1"
0(
1+
01
b11001011000110110000101010000110 B
#492000
b00100 $
b11110 %
b00001110010100011010001101111000 &
b11000001000001101000010110100111 '
b00100 -
b11110 .
b00001110010100011010001101111000 /
b11000001000001101000010110100111 0
#493000
1(
b10111100010001000010100110101101 )
b11111 *
11
b10111100010001000010100110101101 2
b11111 3
#495000
0"
0+
#500000
1"
0(
1+
01
b10111100010001000010100110101101 S
#502000
b10010 $
b00100 %
b00110111111100111000101111111010 &
b00001110010100011010001101111000 '
b10010 -
b00100 .
b00110111111100111000101111111010 /
b00001110010100011010001101111000 0
#503000
1(
b11010110110100101000001010111100 )
b01010 *
11
b11010110110100101000001010111100 2
b01010 3
#505000
0"
0+
#510000
1"
0(
1+
01
b11010110110100101000001010111100 >
#512000
b00100 $
b00110 %
b00001110010100011010001101111000 &
b11110010011111101110101011110001 '
b00100 -
b00110 .
b00001110010100011010001101111000 /
b11110010011111101110101011110001 0
#513000
1(
b01111111000001010000011011001100 )
b01101 *
11
b01111111000001010000011011001100 2
b01101 3
#515000
0"
0+
#520000
1"
0(
1+
01
b01111111000001010000011011001100 A
#522000
b10000 $
b10011 %
b00000000000000000000000000000000 &
b11111000110100011111110111011110 '
b10000 -
b10011 .
b00000000000000000000000000000000 /
b11111000110100011111110111011110 0
#523000
1(
b01110101110001011111110000010010 )
b00100 *
11
b01110101110001011111110000010010 2
b00100 3
#525000
0"
0+
#530000
1"
0(
1+
01
b01110101110001011111110000010010 8
#532000
b01100 $
b10001 %
b01001011000101101110001001010001 &
b00000000111100110011001010000111 '
b01100 -
b10001 .
b01001011000101101110001001010001 /
b00000000111100110011001010000111 0
#533000
1(
b01101101111001000100100111011100 )
b01010 *
11
b01101101111001000100100111011100 2
b01010 3
#535000
0"
0+
#540000
1"
0(
1+
01
b01101101111001000100100111011100 >
#542000
b10111 $
b11100 %
b00000000000000000000000000000000 &
b00000000000000000000000000000000 '
b10111 -
b11100 .
b00000000000000000000000000000000 /
b00000000000000000000000000000000 0
#543000
1(
b11110001110111010001110011001111 )
b10001 *
11
b11110001110111010001110011001111 2
b10001 3
#545000
0"
0+
#550000
1"
0(
1+
01
b11110001110111010001110011001111 E
#552000
b11110 $
b00100 %
b11000001000001101000010110100111 &
b01110101110001011111110000010010 '
b11110 -
b00100 .
b11000001000001101000010110100111 /
b01110101110001011111110000010010 0
#553000
1(
b00001110100001000011110111110000 )
11
b00001110100001000011110111110000 2
#555000
0"
0+
#560000
1"
0(
1+
01
b00001110100001000011110111110000 E
#562000
b00110 $
b10110 %
b11110010011111101110101011110001 &
b00000000000000000000000000000000 '
b00110 -
b10110 .
b11110010011111101110101011110001 /
b00000000000000000000000000000000 0
#563000
1(
b01011011100110100000010001000100 )
b00110 *
11
b01011011100110100000010001000100 2
b00110 3
#565000
0"
0+
#570000
1"
b01011011100110100000010001000100 &
0(
1+
b01011011100110100000010001000100 /
01
b01011011100110100000010001000100 :
#572000
b11011 $
b00110 %
b00000000000000000000000000000000 &
b01011011100110100000010001000100 '
b11011 -
b00110 .
b00000000000000000000000000000000 /
b01011011100110100000010001000100 0
#573000
1(
b11100110010101101001100111101110 )
11
b11100110010101101001100111101110 2
#575000
0"
0+
#580000
1"
b11100110010101101001100111101110 '
0(
1+
b11100110010101101001100111101110 0
01
b11100110010101101001100111101110 :
#582000
b11001 $
b01101 %
b10100100111001100111100001001111 &
b01111111000001010000011011001100 '
b11001 -
b01101 .
b10100100111001100111100001001111 /
b01111111000001010000011011001100 0
#583000
1(
b00001101001011010011001000010001 )
b00111 *
11
b00001101001011010011001000010001 2
b00111 3
#585000
0"
0+
#590000
1"
0(
1+
01
b00001101001011010011001000010001 ;
#592000
b01110 $
b11011 %
b11001011000110110000101010000110 &
b00000000000000000000000000000000 '
b01110 -
b11011 .
b11001011000110110000101010000110 /
b00000000000000000000000000000000 0
#593000
1(
b01011110001010101100010100101111 )
b11001 *
11
b01011110001010101100010100101111 2
b11001 3
#595000
0"
0+
#600000
1"
0(
1+
01
b01011110001010101100010100101111 M
#602000
b00101 $
b10101 %
b10101111101010011110001010010001 &
b01111011111001011101010011101010 '
b00101 -
b10101 .
b10101111101010011110001010010001 /
b01111011111001011101010011101010 0
#603000
1(
b11101001001100011000011000111101 )
b10011 *
11
b11101001001100011000011000111101 2
b10011 3
#605000
0"
0+
#610000
1"
0(
1+
01
b11101001001100011000011000111101 G
#612000
b00110 $
b01110 %
b11100110010101101001100111101110 &
b11001011000110110000101010000110 '
b00110 -
b01110 .
b11100110010101101001100111101110 /
b11001011000110110000101010000110 0
#613000
1(
b10110100010001110101101110011010 )
b01000 *
11
b10110100010001110101101110011010 2
b01000 3
#615000
0"
0+
#620000
1"
0(
1+
01
b10110100010001110101101110011010 <
#622000
b01101 $
b00010 %
b01111111000001010000011011001100 &
b11011001011011010111010001111010 '
b01101 -
b00010 .
b01111111000001010000011011001100 /
b11011001011011010111010001111010 0
#623000
1(
b00101111001010101011110000101101 )
b00111 *
11
b00101111001010101011110000101101 2
b00111 3
#625000
0"
0+
#630000
1"
0(
1+
01
b00101111001010101011110000101101 ;
#632000
b00001 $
b10101 %
b00000000000000000000000000000000 &
b01111011111001011101010011101010 '
b00001 -
b10101 .
b00000000000000000000000000000000 /
b01111011111001011101010011101010 0
#633000
1(
b11000011101000101010110001011111 )
b10101 *
11
b11000011101000101010110001011111 2
b10101 3
#635000
0"
0+
#640000
1"
b11000011101000101010110001011111 '
0(
1+
b11000011101000101010110001011111 0
01
b11000011101000101010110001011111 I
#642000
b10001 $
b01010 %
b00001110100001000011110111110000 &
b01101101111001000100100111011100 '
b10001 -
b01010 .
b00001110100001000011110111110000 /
b01101101111001000100100111011100 0
#643000
1(
b01101001000011110110101100110110 )
b10001 *
11
b01101001000011110110101100110110 2
b10001 3
#645000
0"
0+
#650000
1"
b01101001000011110110101100110110 &
0(
1+
b01101001000011110110101100110110 /
01
b01101001000011110110101100110110 E
#652000
b00111 $
b11011 %
b00101111001010101011110000101101 &
b00000000000000000000000000000000 '
b00111 -
b11011 .
b00101111001010101011110000101101 /
b00000000000000000000000000000000 0
#653000
1(
b10111010001101110100011000101001 )
b01101 *
11
b10111010001101110100011000101001 2
b01101 3
#655000
0"
0+
#660000
1"
0(
1+
01
b10111010001101110100011000101001 A
#662000
b01110 $
b01010 %
b11001011000110110000101010000110 &
b01101101111001000100100111011100 '
b01110 -
b01010 .
b11001011000110110000101010000110 /
b01101101111001000100100111011100 0
#663000
1(
b11101101000000100101110100011001 )
b10111 *
11
b11101101000000100101110100011001 2
b10111 3
#665000
0"
0+
#670000
1"
0(
1+
01
b11101101000000100101110100011001 K
#672000
b11101 $
b10110 %
b00000000000000000000000000000000 &
b00000000000000000000000000000000 '
b11101 -
b10110 .
b00000000000000000000000000000000 /
b00000000000000000000000000000000 0
#673000
1(
b01000100000110001100111011011110 )
b11100 *
11
b01000100000110001100111011011110 2
b11100 3
#675000
0"
0+
#680000
1"
0(
1+
01
b01000100000110001100111011011110 P
#682000
b10000 $
b11011 %
b10000 -
b11011 .
#683000
1(
b01000001001011011001001010010001 )
b01110 *
11
b01000001001011011001001010010001 2
b01110 3
#685000
0"
0+
#690000
1"
0(
1+
01
b01000001001011011001001010010001 B
#692000
b11110 $
b00101 %
b11000001000001101000010110100111 &
b10101111101010011110001010010001 '
b11110 -
b00101 .
b11000001000001101000010110100111 /
b10101111101010011110001010010001 0
#693000
1(
b10000110111111001000100101000101 )
b00001 *
11
b10000110111111001000100101000101 2
b00001 3
#695000
0"
0+
#700000
1"
0(
1+
01
b10000110111111001000100101000101 5
#702000
b10111 $
b00111 %
b11101101000000100101110100011001 &
b00101111001010101011110000101101 '
b10111 -
b00111 .
b11101101000000100101110100011001 /
b00101111001010101011110000101101 0
#703000
1(
b11000000011000010100100000100011 )
b10101 *
11
b11000000011000010100100000100011 2
b10101 3
#705000
0"
0+
#710000
1"
0(
1+
01
b11000000011000010100100000100011 I
#712000
b00011 $
b10011 %
b11111001011011110111110011101101 &
b11101001001100011000011000111101 '
b00011 -
b10011 .
b11111001011011110111110011101101 /
b11101001001100011000011000111101 0
#713000
1(
b11111000001100111010010111000001 )
b10110 *
11
b11111000001100111010010111000001 2
b10110 3
#715000
0"
0+
#720000
1"
0(
1+
01
b11111000001100111010010111000001 J
#722000
b01000 $
b10100 %
b10110100010001110101101110011010 &
b10010000001111000111010111110101 '
b01000 -
b10100 .
b10110100010001110101101110011010 /
b10010000001111000111010111110101 0
#723000
1(
b00001010111111110000101000010100 )
b11111 *
11
b00001010111111110000101000010100 2
b11111 3
#725000
0"
0+
#730000
1"
0(
1+
01
b00001010111111110000101000010100 S
#732000
b10000 $
b01000 %
b00000000000000000000000000000000 &
b10110100010001110101101110011010 '
b10000 -
b01000 .
b00000000000000000000000000000000 /
b10110100010001110101101110011010 0
#733000
1(
b10001011011000001110101011011011 )
b11100 *
11
b10001011011000001110101011011011 2
b11100 3
#735000
0"
0+
#740000
1"
0(
1+
01
b10001011011000001110101011011011 P
#742000
b01111 $
b11001 %
b01111010000011111000111110011000 &
b01011110001010101100010100101111 '
b01111 -
b11001 .
b01111010000011111000111110011000 /
b01011110001010101100010100101111 0
#743000
1(
b01111110100011000110001010111011 )
b11111 *
11
b01111110100011000110001010111011 2
b11111 3
#745000
0"
0+
#750000
1"
0(
1+
01
b01111110100011000110001010111011 S
#752000
b01110 $
b01000 %
b01000001001011011001001010010001 &
b10110100010001110101101110011010 '
b01110 -
b01000 .
b01000001001011011001001010010001 /
b10110100010001110101101110011010 0
#753000
1(
b01101111111111011110010111101010 )
b10111 *
11
b01101111111111011110010111101010 2
b10111 3
#755000
0"
0+
#760000
1"
0(
1+
01
b01101111111111011110010111101010 K
#762000
b01111 $
b01011 %
b01111010000011111000111110011000 &
b00000000000000000000000000000000 '
b01111 -
b01011 .
b01111010000011111000111110011000 /
b00000000000000000000000000000000 0
#763000
1(
b10111101100111100000000110011101 )
b10001 *
11
b10111101100111100000000110011101 2
b10001 3
#765000
0"
0+
#770000
1"
0(
1+
01
b10111101100111100000000110011101 E
#772000
b10010 $
b11110 %
b00110111111100111000101111111010 &
b11000001000001101000010110100111 '
b10010 -
b11110 .
b00110111111100111000101111111010 /
b11000001000001101000010110100111 0
#773000
1(
b10101000101110011001001111010110 )
b00011 *
11
b10101000101110011001001111010110 2
b00011 3
#775000
0"
0+
#780000
1"
0(
1+
01
b10101000101110011001001111010110 7
#782000
b11010 $
b00100 %
b00101001001010110011001001111100 &
b01110101110001011111110000010010 '
b11010 -
b00100 .
b00101001001010110011001001111100 /
b01110101110001011111110000010010 0
#783000
1(
b01111110001100001001110110110101 )
b00001 *
11
b01111110001100001001110110110101 2
b00001 3
#785000
0"
0+
