Single_Cycle/Mod_1_1c_ALU/alu.sv
module alu (
    input logic [2:0] alu_control, //Signal that determines what operation of the ALU is asserted
    input logic [31:0] operand1, //First operand for the ALU operation
    input logic [31:0] operand2, //Second operand for the ALU operation

    output logic [31:0] alu_result, //Result of the ALU operation
    output logic zero //Signal that is asserted if the result of the ALU operation is zero
);


always_comb begin
    case (alu_control)
        3'b000: alu_result = operand1 + operand2; //Addition
        default: alu_result = 32'b0; //Default case, result is zero
    endcase
end


assign zero = alu_result == 32'b0; //Zero if ALU output is also 0

endmodule

Single_Cycle/Mod_1_1c_ALU/dump.vcd
$version Generated by VerilatedVcd $end
$timescale 1ps $end
 $scope module $rootio $end
  $var wire 3 " alu_control [2:0] $end
  $var wire 32 # operand1 [31:0] $end
  $var wire 32 $ operand2 [31:0] $end
  $var wire 32 % alu_result [31:0] $end
  $var wire 1 & zero $end
 $upscope $end
 $scope module alu $end
  $var wire 3 ' alu_control [2:0] $end
  $var wire 32 ( operand1 [31:0] $end
  $var wire 32 ) operand2 [31:0] $end
  $var wire 32 * alu_result [31:0] $end
  $var wire 1 + zero $end
 $upscope $end
$enddefinitions $end


#0
b000 "
b00000000000000000000000000000000 #
b00000000000000000000000000000000 $
b00000000000000000000000000000000 %
1&
b000 '
b00000000000000000000000000000000 (
b00000000000000000000000000000000 )
b00000000000000000000000000000000 *
1+
#1000
b10000001110111011100000000101100 #
b10110011110000010000000001010010 $
b00110101100111101100000001111110 %
0&
b10000001110111011100000000101100 (
b10110011110000010000000001010010 )
b00110101100111101100000001111110 *
0+
#2000
b10110010010000010100011001110100 #
b00000111011101110000011110101111 $
b10111001101110000100111000100011 %
b10110010010000010100011001110100 (
b00000111011101110000011110101111 )
b10111001101110000100111000100011 *
#3000
b00111110101100101010001111101111 #
b01110010010001011001101100011000 $
b10110000111110000011111100000111 %
b00111110101100101010001111101111 (
b01110010010001011001101100011000 )
b10110000111110000011111100000111 *
#4000
b01110000100010011111011011100110 #
b10010111001111101100111010010111 $
b00000111110010001100010101111101 %
b01110000100010011111011011100110 (
b10010111001111101100111010010111 )
b00000111110010001100010101111101 *
#5000
b00001011000100101011100010110111 #
b01011011010011011111011001000110 $
b01100110011000001010111011111101 %
b00001011000100101011100010110111 (
b01011011010011011111011001000110 )
b01100110011000001010111011111101 *
#6000
b01000001000011110100111100011100 #
b11011100010101000001101010011111 $
b00011101011000110110100110111011 %
b01000001000011110100111100011100 (
b11011100010101000001101010011111 )
b00011101011000110110100110111011 *
#7000
b11010101101110000001010010010010 #
b10011101110000010001001001111011 $
b01110011011110010010011100001101 %
b11010101101110000001010010010010 (
b10011101110000010001001001111011 )
b01110011011110010010011100001101 *
#8000
b11001110001100000011010111000110 #
b11100011111001110000011001101000 $
b10110010000101110011110000101110 %
b11001110001100000011010111000110 (
b11100011111001110000011001101000 )
b10110010000101110011110000101110 *
#9000
b10011001001011000000111111101010 #
b00011110111011010111000001111000 $
b10111000000110011000000001100010 %
b10011001001011000000111111101010 (
b00011110111011010111000001111000 )
b10111000000110011000000001100010 *
#10000
b01010001000100110111111111111111 #
b11110000111101001000000010111101 $
b01000010000010000000000010111100 %
b01010001000100110111111111111111 (
b11110000111101001000000010111101 )
b01000010000010000000000010111100 *
#11000
b10110100111111100110110000011110 #
b01100000110000001111100000001011 $
b00010101101111110110010000101001 %
b10110100111111100110110000011110 (
b01100000110000001111100000001011 )
b00010101101111110110010000101001 *
#12000
b10010010000111001111000011111100 #
b11101001100010011101000011110000 $
b01111011101001101100000111101100 %
b10010010000111001111000011111100 (
b11101001100010011101000011110000 )
b01111011101001101100000111101100 *
#13000
b10001100100011100010101011110110 #
b10010001011011111001001001010111 $
b00011101111111011011110101001101 %
b10001100100011100010101011110110 (
b10010001011011111001001001010111 )
b00011101111111011011110101001101 *
#14000
b10110000011011000110111101001110 #
b01001010000111100101000010001110 $
b11111010100010101011111111011100 %
b10110000011011000110111101001110 (
b01001010000111100101000010001110 )
b11111010100010101011111111011100 *
#15000
b01000100100001000100100001101111 #
b00111010111011100101011101000111 $
b01111111011100101001111110110110 %
b01000100100001000100100001101111 (
b00111010111011100101011101000111 )
b01111111011100101001111110110110 *
#16000
b11000110010101100010100011111100 #
b11010100111100001100001111011010 $
b10011011010001101110110011010110 %
b11000110010101100010100011111100 (
b11010100111100001100001111011010 )
b10011011010001101110110011010110 *
#17000
b00111000001100110000100000011001 #
b10001000110111000010101011111101 $
b11000001000011110011001100010110 %
b00111000001100110000100000011001 (
b10001000110111000010101011111101 )
b11000001000011110011001100010110 *
#18000
b01011010110001000000000001011000 #
b00011101110000100110000001000010 $
b01111000100001100110000010011010 %
b01011010110001000000000001011000 (
b00011101110000100110000001000010 )
b01111000100001100110000010011010 *
#19000
b01010001110101010010010110110101 #
b00111010101111001010110010000110 $
b10001100100100011101001000111011 %
b01010001110101010010010110110101 (
b00111010101111001010110010000110 )
b10001100100100011101001000111011 *
#20000
b00100010001010000011110001001111 #
b01001101010000110010001101101100 $
b01101111011010110101111110111011 %
b00100010001010000011110001001111 (
b01001101010000110010001101101100 )
b01101111011010110101111110111011 *
#21000
b00011010001100001001001101110101 #
b10111000100111010101111111101111 $
b11010010110011011111001101100100 %
b00011010001100001001001101110101 (
b10111000100111010101111111101111 )
b11010010110011011111001101100100 *
#22000
b10010001110111111010110110001111 #
b10011110001110001000011101011111 $
b00110000000110000011010011101110 %
b10010001110111111010110110001111 (
b10011110001110001000011101011111 )
b00110000000110000011010011101110 *
#23000
b10010010000000101100011101111011 #
b11110101101001101001010001110000 $
b10000111101010010101101111101011 %
b10010010000000101100011101111011 (
b11110101101001101001010001110000 )
b10000111101010010101101111101011 *
#24000
b01011001110011101011101111111111 #
b10110000111110101000010101100100 $
b00001010110010010100000101100011 %
b01011001110011101011101111111111 (
b10110000111110101000010101100100 )
b00001010110010010100000101100011 *
#25000
b00110010100011001110111101000000 #
b10101100110011110001011001110111 $
b11011111010111000000010110110111 %
b00110010100011001110111101000000 (
b10101100110011110001011001110111 )
b11011111010111000000010110110111 *
#26000
b10110011101010111010000110011001 #
b10000111100011000011101010101100 $
b00111011001101111101110001000101 %
b10110011101010111010000110011001 (
b10000111100011000011101010101100 )
b00111011001101111101110001000101 *
#27000
b01111010100000000111101101110011 #
b10101111101111111101100101100110 $
b00101010010000000101010011011001 %
b01111010100000000111101101110011 (
b10101111101111111101100101100110 )
b00101010010000000101010011011001 *
#28000
b00101001111111101000001011101010 #
b11000001001111010010000111101100 $
b11101011001110111010010011010110 %
b00101001111111101000001011101010 (
b11000001001111010010000111101100 )
b11101011001110111010010011010110 *
#29000
b11100110000101100011001100101101 #
b01001101011001110001001001110101 $
b00110011011111010100010110100010 %
b11100110000101100011001100101101 (
b01001101011001110001001001110101 )
b00110011011111010100010110100010 *
#30000
b00001111010011101011111100001010 #
b01011110001100101001110011010000 $
b01101101100000010101101111011010 %
b00001111010011101011111100001010 (
b01011110001100101001110011010000 )
b01101101100000010101101111011010 *
#31000
b01000011100010100001000110101011 #
b11011101111011100000111010001100 $
b00100001011110000010000000110111 %
b01000011100010100001000110101011 (
b11011101111011100000111010001100 )
b00100001011110000010000000110111 *
#32000
b01011011101110001010011100010001 #
b11111000010010101101011000000100 $
b01010100000000110111110100010101 %
b01011011101110001010011100010001 (
b11111000010010101101011000000100 )
b01010100000000110111110100010101 *
#33000
b01110111100101010101001101111111 #
b11110000010111011010010111100111 $
b01100111111100101111100101100110 %
b01110111100101010101001101111111 (
b11110000010111011010010111100111 )
b01100111111100101111100101100110 *
#34000
b11001000111111000001011001011100 #
b10010101101100110010110010100000 $
b01011110101011110100001011111100 %
b11001000111111000001011001011100 (
b10010101101100110010110010100000 )
b01011110101011110100001011111100 *
#35000
b00110011101101101001000111011011 #
b01000100011101010000010011100011 $
b01111000001010111001011010111110 %
b00110011101101101001000111011011 (
b01000100011101010000010011100011 )
b01111000001010111001011010111110 *
#36000
b10011001001101101110010001100011 #
b11101110011111001101011101011101 $
b10000111101100111011101111000000 %
b10011001001101101110010001100011 (
b11101110011111001101011101011101 )
b10000111101100111011101111000000 *
#37000
b11111110000001111110001001111000 #
b10011110111100110001111001010000 $
b10011100111110110000000011001000 %
b11111110000001111110001001111000 (
b10011110111100110001111001010000 )
b10011100111110110000000011001000 *
#38000
b00111001111011000001101010111001 #
b01010011011000110010110111011101 $
b10001101010011110100100010010110 %
b00111001111011000001101010111001 (
b01010011011000110010110111011101 )
b10001101010011110100100010010110 *
#39000
b11001010100000011011111000011100 #
b10100001100010011100011011010100 $
b01101100000010111000010011110000 %
b11001010100000011011111000011100 (
b10100001100010011100011011010100 )
b01101100000010111000010011110000 *
#40000
b10111011101101101111111101011000 #
b11001011011111010101111001100110 $
b10000111001101000101110110111110 %
b10111011101101101111111101011000 (
b11001011011111010101111001100110 )
b10000111001101000101110110111110 *
#41000
b11101111100101110010100000010100 #
b01001100001010101011011001010100 $
b00111011110000011101111001101000 %
b11101111100101110010100000010100 (
b01001100001010101011011001010100 )
b00111011110000011101111001101000 *
#42000
b10101100101011111010110101001000 #
b01101000000100111010111110111001 $
b00010100110000110101110100000001 %
b10101100101011111010110101001000 (
b01101000000100111010111110111001 )
b00010100110000110101110100000001 *
#43000
b10001111110001111100110111001101 #
b01100101011110110111000101101011 $
b11110101010000110011111100111000 %
b10001111110001111100110111001101 (
b01100101011110110111000101101011 )
b11110101010000110011111100111000 *
#44000
b00111001110001111100011000101001 #
b10101100111010001001100100000110 $
b11100110101100000101111100101111 %
b00111001110001111100011000101001 (
b10101100111010001001100100000110 )
b11100110101100000101111100101111 *
#45000
b11000011000001011100101000101110 #
b01100111010100011100001110000110 $
b00101010010101111000110110110100 %
b11000011000001011100101000101110 (
b01100111010100011100001110000110 )
b00101010010101111000110110110100 *
#46000
b01011101011010111000000000011001 #
b10101101000111100011010011000001 $
b00001010100010011011010011011010 %
b01011101011010111000000000011001 (
b10101101000111100011010011000001 )
b00001010100010011011010011011010 *
#47000
b10100011111001000000100000010011 #
b11111110001110010101110110010110 $
b10100010000111010110010110101001 %
b10100011111001000000100000010011 (
b11111110001110010101110110010110 )
b10100010000111010110010110101001 *
#48000
b10010000001010000011111001011001 #
b10101111100101011111101101111101 $
b00111111101111100011100111010110 %
b10010000001010000011111001011001 (
b10101111100101011111101101111101 )
b00111111101111100011100111010110 *
#49000
b10011000001100100110001100110111 #
b00110100110000010101101011101111 $
b11001100111100111011111000100110 %
b10011000001100100110001100110111 (
b00110100110000010101101011101111 )
b11001100111100111011111000100110 *
#50000
b11111100101100101000000101000110 #
b10101110010110100100111010001011 $
b10101011000011001100111111010001 %
b11111100101100101000000101000110 (
b10101110010110100100111010001011 )
b10101011000011001100111111010001 *
#51000
b10100111010011011110110100110000 #
b01010100001010100111111100010110 $
b11111011011110000110110001000110 %
b10100111010011011110110100110000 (
b01010100001010100111111100010110 )
b11111011011110000110110001000110 *
#52000
b10111000001110001101010101111110 #
b01110000010110100010110010110011 $
b00101000100100110000001000110001 %
b10111000001110001101010101111110 (
b01110000010110100010110010110011 )
b00101000100100110000001000110001 *
#53000
b10001000111001001100010100101010 #
b00111000010010111111101111000011 $
b11000001001100001100000011101101 %
b10001000111001001100010100101010 (
b00111000010010111111101111000011 )
b11000001001100001100000011101101 *
#54000
b11111100010111100001100010100110 #
b11011010101101110011001011001101 $
b11010111000101010100101101110011 %
b11111100010111100001100010100110 (
b11011010101101110011001011001101 )
b11010111000101010100101101110011 *
#55000
b01100101101001001000000101010010 #
b00111111010010010100001100100001 $
b10100100111011011100010001110011 %
b01100101101001001000000101010010 (
b00111111010010010100001100100001 )
b10100100111011011100010001110011 *
#56000
b00001010101001100010010001110110 #
b00010110010101011000001000000100 $
b00100000111110111010011001111010 %
b00001010101001100010010001110110 (
b00010110010101011000001000000100 )
b00100000111110111010011001111010 *
#57000
b01100110111110000011011010100100 #
b01011010011100000100111011010010 $
b11000001011010001000010101110110 %
b01100110111110000011011010100100 (
b01011010011100000100111011010010 )
b11000001011010001000010101110110 *
#58000
b10001010100010011010101100111000 #
b01101010010101110110000111111111 $
b11110100111000010000110100110111 %
b10001010100010011010101100111000 (
b01101010010101110110000111111111 )
b11110100111000010000110100110111 *
#59000
b01110001001101000110111000111010 #
b01110011011010111110110111101001 $
b11100100101000000101110000100011 %
b01110001001101000110111000111010 (
b01110011011010111110110111101001 )
b11100100101000000101110000100011 *
#60000
b01010110010100000001010010101100 #
b10010110100010101110000000101111 $
b11101100110110101111010011011011 %
b01010110010100000001010010101100 (
b10010110100010101110000000101111 )
b11101100110110101111010011011011 *
#61000
b01100111010100011101011011111100 #
b10100110101010001000000111100001 $
b00001101111110100101100011011101 %
b01100111010100011101011011111100 (
b10100110101010001000000111100001 )
b00001101111110100101100011011101 *
#62000
b10111111101101010111001000110011 #
b11010111110010010011110101100000 $
b10010111011111101010111110010011 %
b10111111101101010111001000110011 (
b11010111110010010011110101100000 )
b10010111011111101010111110010011 *
#63000
b00111000100100000001001111011000 #
b11010001001101100010010101100111 $
b00001001110001100011100100111111 %
b00111000100100000001001111011000 (
b11010001001101100010010101100111 )
b00001001110001100011100100111111 *
#64000
b01011011001110111010110010000101 #
b10100110111001100001101001101010 $
b00000010001000011100011011101111 %
b01011011001110111010110010000101 (
b10100110111001100001101001101010 )
b00000010001000011100011011101111 *
#65000
b00001000001011101110011010110111 #
b11010100010000010011001111011101 $
b11011100011100000001101010010100 %
b00001000001011101110011010110111 (
b11010100010000010011001111011101 )
b11011100011100000001101010010100 *
#66000
b00101100111110111010000010001001 #
b10011001011011000001010100001000 $
b11000110011001111011010110010001 %
b00101100111110111010000010001001 (
b10011001011011000001010100001000 )
b11000110011001111011010110010001 *
#67000
b11000100100011100110011100010000 #
b11010000111111011011000111100011 $
b10010101100011000001100011110011 %
b11000100100011100110011100010000 (
b11010000111111011011000111100011 )
b10010101100011000001100011110011 *
#68000
b01010111000110010000110000001010 #
b00110000011011001101101000110001 $
b10000111100001011110011000111011 %
b01010111000110010000110000001010 (
b00110000011011001101101000110001 )
b10000111100001011110011000111011 *
#69000
b11001110100110010001001011100001 #
b11001001110000111100010010001110 $
b10011000010111001101011101101111 %
b11001110100110010001001011100001 (
b11001001110000111100010010001110 )
b10011000010111001101011101101111 *
#70000
b11100110001011011010001100011111 #
b11000000110011000101110100100101 $
b10100110111110100000000001000100 %
b11100110001011011010001100011111 (
b11000000110011000101110100100101 )
b10100110111110100000000001000100 *
#71000
b11001100001111111000011000011110 #
b00000110111011001100001000101110 $
b11010011001011000100100001001100 %
b11001100001111111000011000011110 (
b00000110111011001100001000101110 )
b11010011001011000100100001001100 *
#72000
b11111111111010011110000001011000 #
b01011101100011010000110101000100 $
b01011101011101101110110110011100 %
b11111111111010011110000001011000 (
b01011101100011010000110101000100 )
b01011101011101101110110110011100 *
#73000
b00101010010000000101111100111011 #
b10010110111001101111100110110111 $
b11000001001001110101100011110010 %
b00101010010000000101111100111011 (
b10010110111001101111100110110111 )
b11000001001001110101100011110010 *
#74000
b11011101111110101100111000111101 #
b00011110011110101011111100010000 $
b11111100011101011000110101001101 %
b11011101111110101100111000111101 (
b00011110011110101011111100010000 )
b11111100011101011000110101001101 *
#75000
b11001101110010011000011100011000 #
b11000001001000110111011000001010 $
b10001110111011001111110100100010 %
b11001101110010011000011100011000 (
b11000001001000110111011000001010 )
b10001110111011001111110100100010 *
#76000
b01101100010111010000111110011011 #
b11110001101100110010001110111110 $
b01011110000100000011001101011001 %
b01101100010111010000111110011011 (
b11110001101100110010001110111110 )
b01011110000100000011001101011001 *
#77000
b00001000101110011111011000101011 #
b11010110111000001110010011100011 $
b11011111100110101101101100001110 %
b00001000101110011111011000101011 (
b11010110111000001110010011100011 )
b11011111100110101101101100001110 *
#78000
b01011111110110010101000010011010 #
b00010001110110011101111110110011 $
b01110001101100110011000001001101 %
b01011111110110010101000010011010 (
b00010001110110011101111110110011 )
b01110001101100110011000001001101 *
#79000
b11001100000110110000000001110101 #
b11110001100100000000000100011011 $
b10111101101010110000000110010000 %
b11001100000110110000000001110101 (
b11110001100100000000000100011011 )
b10111101101010110000000110010000 *
#80000
b11101100110110011000010101100111 #
b10101111100101011111000100100100 $
b10011100011011110111011010001011 %
b11101100110110011000010101100111 (
b10101111100101011111000100100100 )
b10011100011011110111011010001011 *
#81000
b00100110110111000000010010000100 #
b10111111101001101010011110100000 $
b11100110100000101010110000100100 %
b00100110110111000000010010000100 (
b10111111101001101010011110100000 )
b11100110100000101010110000100100 *
#82000
b00110010110011000000000011010010 #
b01000110010101110101001110001011 $
b01111001001000110101010001011101 %
b00110010110011000000000011010010 (
b01000110010101110101001110001011 )
b01111001001000110101010001011101 *
#83000
b00001000001101101010000000000010 #
b00100001000011011100101000101001 $
b00101001010001000110101000101011 %
b00001000001101101010000000000010 (
b00100001000011011100101000101001 )
b00101001010001000110101000101011 *
#84000
b10000000111001100011110011110101 #
b10101100000101101110001001111011 $
b00101100111111010001111101110000 %
b10000000111001100011110011110101 (
b10101100000101101110001001111011 )
b00101100111111010001111101110000 *
#85000
b10000011111111010101100000001000 #
b01100010001111011111001101111110 $
b11100110001110110100101110000110 %
b10000011111111010101100000001000 (
b01100010001111011111001101111110 )
b11100110001110110100101110000110 *
#86000
b00100000000010001000010001101110 #
b10011001111101011101011110110000 $
b10111001111111100101110000011110 %
b00100000000010001000010001101110 (
b10011001111101011101011110110000 )
b10111001111111100101110000011110 *
#87000
b00111101100011000111101000001000 #
b10010001000001010101101111011100 $
b11001110100100011101010111100100 %
b00111101100011000111101000001000 (
b10010001000001010101101111011100 )
b11001110100100011101010111100100 *
#88000
b01101011101000010010110011000011 #
b11100010101011110110011100111101 $
b01001110010100001001010000000000 %
b01101011101000010010110011000011 (
b11100010101011110110011100111101 )
b01001110010100001001010000000000 *
#89000
b10011011000110000001111000110101 #
b11010111010001010001101101110111 $
b01110010010111010011100110101100 %
b10011011000110000001111000110101 (
b11010111010001010001101101110111 )
b01110010010111010011100110101100 *
#90000
b11010101001100010000010111101111 #
b10101100011011011101000001000101 $
b10000001100111101101011000110100 %
b11010101001100010000010111101111 (
b10101100011011011101000001000101 )
b10000001100111101101011000110100 *
#91000
b00111101001001100010001001011011 #
b10101011100011111101000011111111 $
b11101000101101011111001101011010 %
b00111101001001100010001001011011 (
b10101011100011111101000011111111 )
b11101000101101011111001101011010 *
#92000
b00110001111110111000000101101000 #
b00100010110001000110100000010111 $
b01010100101111111110100101111111 %
b00110001111110111000000101101000 (
b00100010110001000110100000010111 )
b01010100101111111110100101111111 *
#93000
b11110100001010100111001011011010 #
b10010101100011010100010101001011 $
b10001001101101111011100000100101 %
b11110100001010100111001011011010 (
b10010101100011010100010101001011 )
b10001001101101111011100000100101 *
#94000
b10111100111010101111101011001011 #
b11001100010101101010001100101010 $
b10001001010000011001110111110101 %
b10111100111010101111101011001011 (
b11001100010101101010001100101010 )
b10001001010000011001110111110101 *
#95000
b01100100100000110101001000101100 #
b10101001010100110011011100100001 $
b00001101110101101000100101001101 %
b01100100100000110101001000101100 (
b10101001010100110011011100100001 )
b00001101110101101000100101001101 *
#96000
b00110101010100111001011001011111 #
b00010110101011010001111100110100 $
b01001100000000001011010110010011 %
b00110101010100111001011001011111 (
b00010110101011010001111100110100 )
b01001100000000001011010110010011 *
#97000
b01011010000110101001100111110001 #
b10011011110111100111011110100101 $
b11110101111110010001000110010110 %
b01011010000110101001100111110001 (
b10011011110111100111011110100101 )
b11110101111110010001000110010110 *
#98000
b11110100000111011110101001011100 #
b11101100011011010011110010001000 $
b11100000100010110010011011100100 %
b11110100000111011110101001011100 (
b11101100011011010011110010001000 )
b11100000100010110010011011100100 *
#99000
b01010100110000010010010011010000 #
b00111001101110101111001110011101 $
b10001110011111000001100001101101 %
b01010100110000010010010011010000 (
b00111001101110101111001110011101 )
b10001110011111000001100001101101 *
#100000
b01010000111100010101100100000111 #
b00010001101000101100011011000111 $
b01100010100101000001111111001110 %
b01010000111100010101100100000111 (
b00010001101000101100011011000111 )
b01100010100101000001111111001110 *
#101000
b11110100100001100000000000100010 #
b10000110011100110110101110101111 $
b01111010111110010110101111010001 %
b11110100100001100000000000100010 (
b10000110011100110110101110101111 )
b01111010111110010110101111010001 *
#102000
b11100100010010100111111010011011 #
b00010111000010011110000011101000 $
b11111011010101000101111110000011 %
b11100100010010100111111010011011 (
b00010111000010011110000011101000 )
b11111011010101000101111110000011 *
#103000
b10000111011110111100110101100011 #
b10011000001110010100000111101111 $
b00011111101101010000111101010010 %
b10000111011110111100110101100011 (
b10011000001110010100000111101111 )
b00011111101101010000111101010010 *
#104000
b11111110111000011110011111011110 #
b00101111011010001111101000100001 $
b00101110010010101110000111111111 %
b11111110111000011110011111011110 (
b00101111011010001111101000100001 )
b00101110010010101110000111111111 *
#105000
b11010111111000100110111110001011 #
b01010111000000000011010100011100 $
b00101110111000101010010010100111 %
b11010111111000100110111110001011 (
b01010111000000000011010100011100 )
b00101110111000101010010010100111 *
#106000
b00111011010000010011010101101110 #
b00001111001001110000101110011100 $
b01001010011010000100000100001010 %
b00111011010000010011010101101110 (
b00001111001001110000101110011100 )
b01001010011010000100000100001010 *
#107000
b10110011000111000100111011100100 #
b01010101011001010110000110110001 $
b00001000100000011011000010010101 %
b10110011000111000100111011100100 (
b01010101011001010110000110110001 )
b00001000100000011011000010010101 *
#108000
b00001100000110000110101111110011 #
b11100100010011010111110001001010 $
b11110000011001011110100000111101 %
b00001100000110000110101111110011 (
b11100100010011010111110001001010 )
b11110000011001011110100000111101 *
#109000
b01011100000110000010100000010011 #
b10101000100111000011110010110111 $
b00000100101101000110010011001010 %
b01011100000110000010100000010011 (
b10101000100111000011110010110111 )
b00000100101101000110010011001010 *
#110000
b00010000111011010110100010100011 #
b11010010110100001101000000011011 $
b11100011101111100011100010111110 %
b00010000111011010110100010100011 (
b11010010110100001101000000011011 )
b11100011101111100011100010111110 *
#111000
b00001010100010011100011110110111 #
b01101111100111110000101010000100 $
b01111010001010001101001000111011 %
b00001010100010011100011110110111 (
b01101111100111110000101010000100 )
b01111010001010001101001000111011 *
#112000
b01111011011100110111110010100111 #
b01000110000110101010100000000110 $
b11000001100011100010010010101101 %
b01111011011100110111110010100111 (
b01000110000110101010100000000110 )
b11000001100011100010010010101101 *
#113000
b10101000110110011001010001000000 #
b11110001001100001100110001001011 $
b10011010000010100110000010001011 %
b10101000110110011001010001000000 (
b11110001001100001100110001001011 )
b10011010000010100110000010001011 *
#114000
b00011111100111100111000110001010 #
b00100000111100101011000010100100 $
b01000000100100010010001000101110 %
b00011111100111100111000110001010 (
b00100000111100101011000010100100 )
b01000000100100010010001000101110 *
#115000
b11100000110011101100100010100100 #
b01001110101111010111010111101010 $
b00101111100011000011111010001110 %
b11100000110011101100100010100100 (
b01001110101111010111010111101010 )
b00101111100011000011111010001110 *
#116000
b01100001000101100111111100100010 #
b01110111010100101100110100100001 $
b11011000011010010100110001000011 %
b01100001000101100111111100100010 (
b01110111010100101100110100100001 )
b11011000011010010100110001000011 *
#117000
b11101110010110011110110001000100 #
b00101100011101000101101001001001 $
b00011010110011100100011010001101 %
b11101110010110011110110001000100 (
b00101100011101000101101001001001 )
b00011010110011100100011010001101 *
#118000
b00111001111100101000011100000100 #
b01100010001011100111000001000001 $
b10011100001000001111011101000101 %
b00111001111100101000011100000100 (
b01100010001011100111000001000001 )
b10011100001000001111011101000101 *
#119000
b10101111111011100001000100100000 #
b10110110010101001010110100000101 $
b01100110010000101011111000100101 %
b10101111111011100001000100100000 (
b10110110010101001010110100000101 )
b01100110010000101011111000100101 *
#120000
b11111110101101011010110101101001 #
b11001111101001010001100111110101 $
b11001110010110101100011101011110 %
b11111110101101011010110101101001 (
b11001111101001010001100111110101 )
b11001110010110101100011101011110 *
#121000
b01100100010001111010110111011000 #
b11000111110111110001110100111010 $
b00101100001001101100101100010010 %
b01100100010001111010110111011000 (
b11000111110111110001110100111010 )
b00101100001001101100101100010010 *
#122000
b01110011001100101110000010100111 #
b11100000000001001001111001110110 $
b01010011001101110111111100011101 %
b01110011001100101110000010100111 (
b11100000000001001001111001110110 )
b01010011001101110111111100011101 *
#123000
b11101111010100110001111011001011 #
b11100001011000011010000011011010 $
b11010000101101001011111110100101 %
b11101111010100110001111011001011 (
b11100001011000011010000011011010 )
b11010000101101001011111110100101 *
#124000
b10110011111100001011111101011001 #
b10010110010000111001101110101111 $
b01001010001101000101101100001000 %
b10110011111100001011111101011001 (
b10010110010000111001101110101111 )
b01001010001101000101101100001000 *
#125000
b00001010001001010101000010110111 #
b11010100000010110110110010010001 $
b11011110001100001011110101001000 %
b00001010001001010101000010110111 (
b11010100000010110110110010010001 )
b11011110001100001011110101001000 *
#126000
b00010101111101111101111111011101 #
b00000000101100001001010111010111 $
b00010110101010000111010110110100 %
b00010101111101111101111111011101 (
b00000000101100001001010111010111 )
b00010110101010000111010110110100 *
#127000
b11111110111110100111001100101010 #
b10000101110001000110100001101000 $
b10000100101111101101101110010010 %
b11111110111110100111001100101010 (
b10000101110001000110100001101000 )
b10000100101111101101101110010010 *
#128000
b01010100000000110111101111111001 #
b10001011010010011001101001100101 $
b11011111010011010001011001011110 %
b01010100000000110111101111111001 (
b10001011010010011001101001100101 )
b11011111010011010001011001011110 *
#129000
b11110100001100001000011011111010 #
b01001010110001111000010010111011 $
b00111110111110000000101110110101 %
b11110100001100001000011011111010 (
b01001010110001111000010010111011 )
b00111110111110000000101110110101 *
#130000
b10110111001010100000011010011101 #
b10100000000101001110111100111010 $
b01010111001111101111010111010111 %
b10110111001010100000011010011101 (
b10100000000101001110111100111010 )
b01010111001111101111010111010111 *
#131000
b11101101001111000111110111010000 #
b01100001111000111100101000010110 $
b01001111001000000100011111100110 %
b11101101001111000111110111010000 (
b01100001111000111100101000010110 )
b01001111001000000100011111100110 *
#132000
b00010100011101101110100101110100 #
b10010001000110011110110011101010 $
b10100101100100001101011001011110 %
b00010100011101101110100101110100 (
b10010001000110011110110011101010 )
b10100101100100001101011001011110 *
#133000
b01101010111101100110100010110010 #
b00111110111110001100101000010100 $
b10101001111011110011001011000110 %
b01101010111101100110100010110010 (
b00111110111110001100101000010100 )
b10101001111011110011001011000110 *
#134000
b11110100111010011100011100111001 #
b01111011010011101011011011011101 $
b01110000001110000111111000010110 %
b11110100111010011100011100111001 (
b01111011010011101011011011011101 )
b01110000001110000111111000010110 *
#135000
b11101001000000110111101000001000 #
b10111101111111000101110010100000 $
b10100110111111111101011010101000 %
b11101001000000110111101000001000 (
b10111101111111000101110010100000 )
b10100110111111111101011010101000 *
#136000
b00100011110010100101110001010001 #
b10101011110100011110000001111010 $
b11001111100111000011110011001011 %
b00100011110010100101110001010001 (
b10101011110100011110000001111010 )
b11001111100111000011110011001011 *
#137000
b00001011010100000000001011111011 #
b01011111111111111010110011101000 $
b01101011010011111010111111100011 %
b00001011010100000000001011111011 (
b01011111111111111010110011101000 )
b01101011010011111010111111100011 *
#138000
b10101001110101011110000011011110 #
b01011100110100101000100111100011 $
b00000110101010000110101011000001 %
b10101001110101011110000011011110 (
b01011100110100101000100111100011 )
b00000110101010000110101011000001 *
#139000
b00100001001011001111001000000110 #
b01011110111010010000011111111100 $
b10000000000101011111101000000010 %
b00100001001011001111001000000110 (
b01011110111010010000011111111100 )
b10000000000101011111101000000010 *
#140000
b11001011100001000001111000000000 #
b00100101110110001000010110011100 $
b11110001010111001010001110011100 %
b11001011100001000001111000000000 (
b00100101110110001000010110011100 )
b11110001010111001010001110011100 *
#141000
b10100001101100001010001100010110 #
b10111010100000010111010001010110 $
b01011100001100100001011101101100 %
b10100001101100001010001100010110 (
b10111010100000010111010001010110 )
b01011100001100100001011101101100 *
#142000
b10010000001111101011111100100111 #
b00000110001101101011100011011111 $
b10010110011101010111100000000110 %
b10010000001111101011111100100111 (
b00000110001101101011100011011111 )
b10010110011101010111100000000110 *
#143000
b00111000100100111111100001010000 #
b00000101100101001011100011101101 $
b00111110001010001011000100111101 %
b00111000100100111111100001010000 (
b00000101100101001011100011101101 )
b00111110001010001011000100111101 *
#144000
b11001101000111010100101110001111 #
b10101011110100011111010100000101 $
b01111000111011110100000010010100 %
b11001101000111010100101110001111 (
b10101011110100011111010100000101 )
b01111000111011110100000010010100 *
#145000
b10011011000110000110111000001110 #
b01110101101010101111011000101101 $
b00010000110000110110010000111011 %
b10011011000110000110111000001110 (
b01110101101010101111011000101101 )
b00010000110000110110010000111011 *
#146000
b10101000011111001011010101100110 #
b11110011001100100110111011111110 $
b10011011101011110010010001100100 %
b10101000011111001011010101100110 (
b11110011001100100110111011111110 )
b10011011101011110010010001100100 *
#147000
b01110000100100000100101001100000 #
b11011110000110001100011100001001 $
b01001110101010010001000101101001 %
b01110000100100000100101001100000 (
b11011110000110001100011100001001 )
b01001110101010010001000101101001 *
#148000
b10011101100100011010010010100010 #
b10001100001001101111000101100011 $
b00101001101110001001011000000101 %
b10011101100100011010010010100010 (
b10001100001001101111000101100011 )
b00101001101110001001011000000101 *
#149000
b10100110010101110010011000010111 #
b11101100110000110000101010011110 $
b10010011000110100011000010110101 %
b10100110010101110010011000010111 (
b11101100110000110000101010011110 )
b10010011000110100011000010110101 *
#150000
b11000011000101100110000101000001 #
b11111000011011101100110011001100 $
b10111011100001010010111000001101 %
b11000011000101100110000101000001 (
b11111000011011101100110011001100 )
b10111011100001010010111000001101 *
#151000
b10100000001110111111101111111001 #
b00001100010000100010100111111111 $
b10101100011111100010010111111000 %
b10100000001110111111101111111001 (
b00001100010000100010100111111111 )
b10101100011111100010010111111000 *
#152000
b10011110100010100001111111100000 #
b00111110111011010101011011010111 $
b11011101011101110111011010110111 %
b10011110100010100001111111100000 (
b00111110111011010101011011010111 )
b11011101011101110111011010110111 *
